tests/__init__.py
tests/test_totates.py
totates/__init__.py
totates/__main__.py
totates/cli.py
totates-0.0.1.dist-info/METADATA
totates-0.0.1.dist-info/WHEEL
totates-0.0.1.dist-info/entry_points.txt
totates-0.0.1.dist-info/top_level.txt
totates-0.0.1.dist-info/RECORD
