Metadata-Version: 2.1
Name: totates
Version: 0.0.1
Summary: Manage ecmascript components
Home-page: UNKNOWN
Author: Johnny Accot
License: UNKNOWN
Platform: UNKNOWN
Classifier: Programming Language :: Python :: 3
Classifier: License :: OSI Approved :: MIT License
Classifier: Operating System :: OS Independent
Requires-Python: >=3.6
